PyWebScraping/__init__.py
PyWebScraping/utilities.py
PyWebScraping/browsers_handler/__init__.py
PyWebScraping/browsers_handler/data.py
PyWebScraping/browsers_handler/windows.py
PyWebScraping/webdrivers/BaseDriver.py
PyWebScraping/webdrivers/Chrome.py
PyWebScraping/webdrivers/Edge.py
PyWebScraping/webdrivers/FireFox.py
PyWebScraping/webdrivers/Yandex.py
PyWebScraping/webdrivers/__init__.py
PyWebScraping-1.3.13.dist-info/METADATA
PyWebScraping-1.3.13.dist-info/WHEEL
PyWebScraping-1.3.13.dist-info/top_level.txt
PyWebScraping-1.3.13.dist-info/RECORD
