Metadata-Version: 2.2
Name: PyWebScraping
Version: 1.3.13
Summary: PyWebScraping is a Python library for browser automation and web scraping. It supports Chrome, Firefox, Edge, and Yandex, providing a consistent API for managing browser sessions, options, and common actions like scrolling, element interaction, and JavaScript execution.  It also facilitates remote webdriver control.
Author: oddshellnick
Author-email: oddshellnick.programming@gmail.com
Requires-Dist: setuptools
Requires-Dist: selenium~=4.26.1
Requires-Dist: pywebrequests~=1.3.13
Requires-Dist: pywindowscmd~=1.3.6
Requires-Dist: pywin32
Dynamic: author
Dynamic: author-email
Dynamic: description
Dynamic: description-content-type
Dynamic: requires-dist
Dynamic: summary
